cryptocom/__init__.py
cryptocom/client.py
cryptocom/web_sockets.py
crypto.com-0.0.0.dist-info/LICENSE.md
crypto.com-0.0.0.dist-info/METADATA
crypto.com-0.0.0.dist-info/WHEEL
crypto.com-0.0.0.dist-info/top_level.txt
crypto.com-0.0.0.dist-info/RECORD
