Metadata-Version: 2.1
Name: crypto.com
Version: 0.0.0
Summary: A python3 crypto.com API wrapper powered by modern technologies such as asyncio
Home-page: https://git.io/crypto.com
Author: Th0rgal
Author-email: thomas.marchand@tuta.io
License: UNKNOWN
Platform: UNKNOWN
Classifier: Programming Language :: Python :: 3
Classifier: License :: OSI Approved :: MIT License
Classifier: Operating System :: OS Independent
Requires-Python: >=3.6
